enfinite_grafana_setup/__init__.py
enfinite_grafana_setup/install_grafana.py
enfinite_grafana_setup/parameters.py
enfinite_grafana_setup/uninstall_grafana.py
enfinite_grafana_setup/whitelable_grafana.py
enfinite_grafana_setup-0.1.1.dist-info/WHEEL
enfinite_grafana_setup-0.1.1.dist-info/METADATA
enfinite_grafana_setup-0.1.1.dist-info/RECORD
