Metadata-Version: 2.1
Name: enfinite-grafana-setup
Version: 0.1.1
Summary: package for managing grafana setup for enfinite clients
Home-page: https://github.com/Enfinite-Tech/enfinite-grafana-setup/tree/packagev1
Keywords: grafana,enfinite,whitelabeling
Author: Chirag Gupta (cgupta98)
Author-email: cgupta@enfinitetech.com
Requires-Python: >=3.10,<4.0
Classifier: Programming Language :: Python :: 3
Classifier: Programming Language :: Python :: 3.10
Classifier: Programming Language :: Python :: 3.11
Requires-Dist: beautifulsoup4 (>=4.11.1,<5.0.0)
Requires-Dist: requests (>=2.28.1,<3.0.0)
